AES_Hardware/AES_verilog/AES.v
//here we use a assign to combine 4 Sbox together.
//We have achieve 32bit look-up table

module SubBytes(x,y);
    input [31:0] x;
    output [31:0] y;
    //default set is wire 
    //use function to multiple excute the block
    function [7:0] S;//function_id return back value
    input [7:0] x   ;
        case (x)
        0:S= 99;   1:S=124;   2:S=119;   3:S=123;   4:S=242;   5:S=107;   6:S=111;   7:S=197;
        8:S= 48;   9:S=  1;  10:S=103;  11:S= 43;  12:S=254;  13:S=215;  14:S=171;  15:S=118;
       16:S=202;  17:S=130;;;18:S=201;  19:S=125;  20:S=250;  21:S= 89;  22:S= 71;  23:S=240;
       24:S=173;  25:S=212;  26:S=162;  27:S=175;  28:S=156;  29:S=164;  30:S=114;  31:S=192;
       32:S=183;  33:S=253;  34:S=147;  35:S= 38;  36:S= 54;  37:S= 63;  38:S=247;  39:S=204;
       40:S= 52;  41:S=165;  42:S=229;  43:S=241;  44:S=113;  45:S=216;  46:S= 49;  47:S= 21;
       48:S=  4;  49:S=199;  50:S= 35;  51:S=195;  52:S= 24;  53:S=150;  54:S=  5;  55:S=154;
       56:S=  7;  57:S= 18;  58:S=128;  59:S=226;  60:S=235;  61:S= 39;  62:S=178;  63:S=117;
       64:S=  9;  65:S=131;  66:S= 44;  67:S= 26;  68:S= 27;  69:S=110;  70:S= 90;  71:S=160;
       72:S= 82;  73:S= 59;  74:S=214;  75:S=179;  76:S= 41;  77:S=227;  78:S= 47;  79:S=132;
       80:S= 83;  81:S=209;  82:S=  0;  83:S=237;  84:S= 32;  85:S=252;  86:S=177;  87:S= 91;
       88:S=106;  89:S=203;  90:S=190;  91:S= 57;  92:S= 74;  93:S= 76;  94:S= 88;  95:S=207;
       96:S=208;  97:S=239;  98:S=170;  99:S=251; 100:S= 67; 101:S= 77; 102:S= 51; 103:S=133;
      104:S= 69; 105:S=249; 106:S=  2; 107:S=127; 108:S= 80; 109:S= 60; 110:S=159; 111:S=168;
      112:S= 81; 113:S=163; 114:S= 64; 115:S=143; 116:S=146; 117:S=157; 118:S= 56; 119:S=245;
      120:S=188; 121:S=182; 122:S=218; 123:S= 33; 124:S= 16; 125:S=255; 126:S=243; 127:S=210;
      128:S=205; 129:S= 12; 130:S= 19; 131:S=236; 132:S= 95; 133:S=151; 134:S= 68; 135:S= 23;
      136:S=196; 137:S=167; 138:S=126; 139:S= 61; 140:S=100; 141:S= 93; 142:S= 25; 143:S=115;
      144:S= 96; 145:S=129; 146:S= 79; 147:S=220; 148:S= 34; 149:S= 42; 150:S=144; 151:S=136;
      152:S= 70; 153:S=238; 154:S=184; 155:S= 20; 156:S=222; 157:S= 94; 158:S= 11; 159:S=219;
      160:S=224; 161:S= 50; 162:S= 58; 163:S= 10; 164:S= 73; 165:S=  6; 166:S= 36; 167:S= 92;
      168:S=194; 169:S=211; 170:S=172; 171:S= 98; 172:S=145; 173:S=149; 174:S=228; 175:S=121;
      176:S=231; 177:S=200; 178:S= 55; 179:S=109; 180:S=141; 181:S=213; 182:S= 78; 183:S=169;
      184:S=108; 185:S= 86; 186:S=244; 187:S=234; 188:S=101; 189:S=122; 190:S=174; 191:S=  8;
      192:S=186; 193:S=120; 194:S= 37; 195:S= 46; 196:S= 28; 197:S=166; 198:S=180; 199:S=198;
      200:S=232; 201:S=221; 202:S=116; 203:S= 31; 204:S= 75; 205:S=189; 206:S=139; 207:S=138;
      208:S=112; 209:S= 62; 210:S=181; 211:S=102; 212:S= 72; 213:S=  3; 214:S=246; 215:S= 14;
      216:S= 97; 217:S= 53; 218:S= 87; 219:S=185; 220:S=134; 221:S=193; 222:S= 29; 223:S=158;
      224:S=225; 225:S=248; 226:S=152; 227:S= 17; 228:S=105; 229:S=217; 230:S=142; 231:S=148;
      232:S=155; 233:S= 30; 234:S=135; 235:S=233; 236:S=206; 237:S= 85; 238:S= 40; 239:S=223;
      240:S=140; 241:S=161; 242:S=137; 243:S= 13; 244:S=191; 245:S=230; 246:S= 66; 247:S=104;
      248:S= 65; 249:S=153; 250:S= 45; 251:S= 15; 252:S=176; 253:S= 84; 254:S=187; 255:S= 22;
    endcase
    endfunction

    assign y = {S(x[31:24]),S(x[23:16]),S(x[15:8]),S(x[7:0])};
    //continuous assign a value,and the value is type wire
    endmodule



module MixColumns(x,y);
    input [31:0] x;
    output [31:0] y;

    wire [7:0] a3,a2,a1,a0;

    assign a3 = x[31:24];
    assign a2 = x[23:16];
    assign a1 = x[15: 8];
    assign a0 = x[ 7: 0];

    function [7:0] SS;
        input [7:0] data;
        SS = {data[6],data[5],data[4],data[3]^data[7],data[2]^data[7],data[1],data[0]^data[7],data[7]};
    endfunction
    
    // function [7:0] SSS;
    //     input [7:0] data;
    //     SSS = {data[6]^data[7],data[5]^data[6],data[4]^data[7]^data[5],data[3]^data[7]^data[4],data[2]^data[3],data[1]^data[2],data[0]^data[7]^data[1],data[7]^data[0]};
    // endfunction
    assign y = {SS(a3)^(SS(a2)^a2)^a1^a0,a3^SS(a2)^(SS(a1)^a1)^a0,a3^a2^SS(a1)^(SS(a0)^a0),(SS(a3)^a3)^a2^a1^SS(a0)};
    //assign y = {SS(a3)^SSS(a2)^a1^a0,a3^SS(a2)^SSS(a1)^a0,a3^a2^SS(a1)^SSS(a0),SSS(a3)^a2^a1^SS(a0)};
    endmodule

//do not expand the encrypt process,do only one round one time
module Enc(di,ki,Round,dn,ko);
    input [127:0] di;
    input [127:0] ki;
    input [9:0] Round;
    output [127:0] dn;
    output [127:0] ko;

    wire [127:0] sb,sr,mx;
    wire [31:0] kp;

 //subBytes
  SubBytes SB3 (di[127:96], sb[127:96]);
  SubBytes SB2 (di[ 95:64], sb[ 95:64]);
  SubBytes SB1 (di[ 63:32], sb[ 63:32]);
  SubBytes SB0 (di[ 31: 0], sb[ 31: 0]);

//shift_rows
  assign sr = {sb[127:120], sb[ 87: 80], sb[ 47: 40], sb[  7:  0],
               sb[ 95: 88], sb[ 55: 48], sb[ 15:  8], sb[103: 96],
               sb[ 63: 56], sb[ 23: 16], sb[111:104], sb[ 71: 64],
               sb[ 31: 24], sb[119:112], sb[ 79: 72], sb[ 39: 32]};

MixColumns MX3 (sr[127:96],mx[127:96]);
MixColumns MX2 (sr[95:64],mx[95:64]);
MixColumns MX1 (sr[63:32],mx[63:32]);
MixColumns MX0 (sr[31:0],mx[31:0]);

assign dn = ((Round[0] == 1)? sr:mx)^ki;
//The last round don't have the mixcolumn.


function [7:0] rcon;
input [9:0] x;//the round now
casex (x)
    10'bxxxxxxxxx1: rcon = 8'h01;
    10'bxxxxxxxx1x: rcon = 8'h02;
    10'bxxxxxxx1xx: rcon = 8'h04;
    10'bxxxxxx1xxx: rcon = 8'h08;
    10'bxxxxx1xxxx: rcon = 8'h10;
    10'bxxxx1xxxxx: rcon = 8'h20;
    10'bxxx1xxxxxx: rcon = 8'h40;
    10'bxx1xxxxxxx: rcon = 8'h80;
    10'bx1xxxxxxxx: rcon = 8'h1b;
    10'b1xxxxxxxxx: rcon = 8'h36;
endcase
endfunction


SubBytes SBk ({ki[23:16],ki[15:8],ki[7:0],ki[31:24]},kp);

  assign ko[127:96] = ki[127:96] ^ {kp[31:24] ^ rcon(Round), kp[23: 0]};
  assign ko[ 95:64] = ki[ 95:64] ^ ko[127:96];
  assign ko[ 63:32] = ki[ 63:32] ^ ko[ 95:64];
  assign ko[ 31: 0] = ki[ 31: 0] ^ ko[ 63:32];
endmodule


module AES_ENC(Din,Key,Dout,Drin,Krin,Reset,ENK,CLK,BSY,Drout);
  input [127:0] Din;
  input [127:0] Key;
  output [127:0] Dout;
  input Drin;
  input Krin;
  input Reset;
  input ENK;
  input CLK;
  output BSY;
  output Drout;

  reg [127:0] Drg;//Data temp
  reg [127:0] Krg;//Key register
  reg [127:0] KrgT;
  reg [9:0] Rrg;
  reg Droutrg,BSYrg;
  wire [127:0] Dnext,knext;

  Enc EC(Drg,KrgT,Rrg,Dnext,knext);

  assign Drout = Droutrg;
  assign Dout = Drg;
  assign BSY =  BSYrg;

always @(posedge CLK) begin
  if (Reset == 0) 
  begin
    Rrg <= 10'b0000000001;
    Droutrg <= 0;
    BSYrg <=0;
  end
  else if(ENK == 1)
  begin
    if(BSYrg==0)
    begin
      if (Krin == 1)
      begin
        Krg <= Key;
        KrgT <= Key;
        Droutrg <= 0;
      end
      else if (Drin == 1)
      begin
        Rrg <= {Rrg[8:0],Rrg[9]};
        KrgT <= knext;
        Drg <= Din^Krg;
        Droutrg <= 0;
        BSYrg <=1;
      end
    end
    else begin
      Drg <= Dnext;
      if (Rrg[0] == 1)begin
        KrgT <=Krg;
        Droutrg <=1;
        BSYrg<=0;
      end 
      else begin
        Rrg <= {Rrg[8:0],Rrg[9]};
        KrgT <= knext;
      end
    end
  end
end 
    
endmodule

AES_Hardware/AES_verilog/AES_tb.v
`timescale 1ns/1ns
`include "AES.v"

module AES_tb;
parameter CLOCK = 10;
//AES_ENC(Din,Key,Dout,Drin,Krin,Reset,ENK,CLK,BSY,Drout);

reg  [127:0] Din;
reg  [127:0] Key;
reg  Drin;
reg  Krin;
reg  Reset;
reg  EN;
reg  CLK;
wire [127:0] Dout;
wire BSY;
wire Drout;

AES_ENC AES_E(
  .Din(Din),
  .Key(Key),
  .Dout(Dout),
  .Drin(Drin),
  .Krin(Krin),
  .Reset(Reset),
  .ENK(EN),
  .CLK(CLK),
  .BSY(BSY),
  .Drout(Drout)
);


reg [127:0] Keyd,plain_text;
initial Keyd = 128'h000102030405060708090a0b0c0d0e0f; 
initial plain_text = 128'h00112233445566778899aabbccddeeff;

initial CLK = 1;
always #(CLOCK/2)
  CLK <= ~CLK;


initial begin

#(CLOCK/2)
//Reset
EN <= 0;
Reset <= 0;
Krin <= 0;
Drin <=0;
//将所有的信号置0

#(CLOCK)
Reset <=1;
EN <=1 ;
Key <= Keyd;
Krin<=1;

#(CLOCK)
Krin <= 0;
Din <= plain_text;
Drin <=1;
//将数据输入

#(CLOCK)

#(CLOCK*10)
$finish;
end

initial begin
    $dumpfile("wave.vcd");
    //check the wave of the module.
    $dumpvars;
end


endmodule

AES_Hardware/AES_verilog/wave.vcd
$date
	Fri Dec 02 20:40:17 2022
$end
$version
	Icarus Verilog
$end
$timescale
	1ns
$end
$scope module AES_tb $end
$var wire 1 ! Drout $end
$var wire 128 " Dout [127:0] $end
$var wire 1 # BSY $end
$var reg 1 $ CLK $end
$var reg 128 % Din [127:0] $end
$var reg 1 & Drin $end
$var reg 1 ' EN $end
$var reg 128 ( Key [127:0] $end
$var reg 128 ) Keyd [127:0] $end
$var reg 1 * Krin $end
$var reg 1 + Reset $end
$var reg 128 , plain_text [127:0] $end
$scope module AES_E $end
$var wire 1 # BSY $end
$var wire 1 $ CLK $end
$var wire 128 - Din [127:0] $end
$var wire 128 . Dout [127:0] $end
$var wire 1 & Drin $end
$var wire 1 ! Drout $end
$var wire 1 ' ENK $end
$var wire 128 / Key [127:0] $end
$var wire 1 * Krin $end
$var wire 1 + Reset $end
$var wire 128 0 knext [127:0] $end
$var wire 128 1 Dnext [127:0] $end
$var reg 1 2 BSYrg $end
$var reg 128 3 Drg [127:0] $end
$var reg 1 4 Droutrg $end
$var reg 128 5 Krg [127:0] $end
$var reg 128 6 KrgT [127:0] $end
$var reg 10 7 Rrg [9:0] $end
$scope module EC $end
$var wire 10 8 Round [9:0] $end
$var wire 128 9 di [127:0] $end
$var wire 128 : dn [127:0] $end
$var wire 128 ; ki [127:0] $end
$var wire 128 < sr [127:0] $end
$var wire 128 = sb [127:0] $end
$var wire 128 > mx [127:0] $end
$var wire 32 ? kp [31:0] $end
$var wire 128 @ ko [127:0] $end
$scope function rcon $end
$var reg 10 A x [9:0] $end
$upscope $end
$scope module MX0 $end
$var wire 32 B x [31:0] $end
$var wire 32 C y [31:0] $end
$var wire 8 D a3 [7:0] $end
$var wire 8 E a2 [7:0] $end
$var wire 8 F a1 [7:0] $end
$var wire 8 G a0 [7:0] $end
$scope function SS $end
$var reg 8 H data [7:0] $end
$upscope $end
$upscope $end
$scope module MX1 $end
$var wire 32 I x [31:0] $end
$var wire 32 J y [31:0] $end
$var wire 8 K a3 [7:0] $end
$var wire 8 L a2 [7:0] $end
$var wire 8 M a1 [7:0] $end
$var wire 8 N a0 [7:0] $end
$scope function SS $end
$var reg 8 O data [7:0] $end
$upscope $end
$upscope $end
$scope module MX2 $end
$var wire 32 P x [31:0] $end
$var wire 32 Q y [31:0] $end
$var wire 8 R a3 [7:0] $end
$var wire 8 S a2 [7:0] $end
$var wire 8 T a1 [7:0] $end
$var wire 8 U a0 [7:0] $end
$scope function SS $end
$var reg 8 V data [7:0] $end
$upscope $end
$upscope $end
$scope module MX3 $end
$var wire 32 W x [31:0] $end
$var wire 32 X y [31:0] $end
$var wire 8 Y a3 [7:0] $end
$var wire 8 Z a2 [7:0] $end
$var wire 8 [ a1 [7:0] $end
$var wire 8 \ a0 [7:0] $end
$scope function SS $end
$var reg 8 ] data [7:0] $end
$upscope $end
$upscope $end
$scope module SB0 $end
$var wire 32 ^ x [31:0] $end
$var wire 32 _ y [31:0] $end
$scope function S $end
$var reg 8 ` x [7:0] $end
$upscope $end
$upscope $end
$scope module SB1 $end
$var wire 32 a x [31:0] $end
$var wire 32 b y [31:0] $end
$scope function S $end
$var reg 8 c x [7:0] $end
$upscope $end
$upscope $end
$scope module SB2 $end
$var wire 32 d x [31:0] $end
$var wire 32 e y [31:0] $end
$scope function S $end
$var reg 8 f x [7:0] $end
$upscope $end
$upscope $end
$scope module SB3 $end
$var wire 32 g x [31:0] $end
$var wire 32 h y [31:0] $end
$scope function S $end
$var reg 8 i x [7:0] $end
$upscope $end
$upscope $end
$scope module SBk $end
$var wire 32 j x [31:0] $end
$var wire 32 k y [31:0] $end
$scope function S $end
$var reg 8 l x [7:0] $end
$upscope $end
$upscope $end
$upscope $end
$upscope $end
$upscope $end
$enddefinitions $end
#0
$dumpvars
bx l
bx k
bx j
bx i
bx h
bx g
bx f
bx e
bx d
bx c
bx b
bx a
bx `
bx _
bx ^
bx ]
bx \
bx [
bx Z
bx Y
bx X
bx W
bx V
bx U
bx T
bx S
bx R
bx Q
bx P
bx O
bx N
bx M
bx L
bx K
bx J
bx I
bx H
bx G
bx F
bx E
bx D
bx C
bx B
bx A
bx @
bx ?
bx >
bx =
bx <
bx ;
bx :
bx 9
bx 8
bx 7
bx 6
bx 5
x4
bx 3
x2
bx 1
bx 0
bx /
bx .
bx -
b100010010001000110011010001000101010101100110011101111000100010011001101010101011101111001100110111011110111011111111 ,
x+
x*
b10000001000000011000001000000010100000110000001110000100000001001000010100000101100001100000011010000111000001111 )
bx (
x'
x&
bx %
1$
x#
bx "
x!
$end
#5
0&
0*
0+
0'
0$
#10
b1 A
0#
02
0!
04
b1 7
b1 8
1$
#15
0$
1*
b10000001000000011000001000000010100000110000001110000100000001001000010100000101100001100000011010000111000001111 (
b10000001000000011000001000000010100000110000001110000100000001001000010100000101100001100000011010000111000001111 /
1'
1+
#20
b11010110101010100111010011111101110100101010111101110010111110101101101010100110011110001111000111010110101010110111011011111110 0
b11010110101010100111010011111101110100101010111101110010111110101101101010100110011110001111000111010110101010110111011011111110 @
b11010111101010110111011011111110 ?
b11010111101010110111011011111110 k
b1101 l
b1101000011100000111100001100 j
b10000001000000011000001000000010100000110000001110000100000001001000010100000101100001100000011010000111000001111 6
b10000001000000011000001000000010100000110000001110000100000001001000010100000101100001100000011010000111000001111 ;
b10000001000000011000001000000010100000110000001110000100000001001000010100000101100001100000011010000111000001111 5
1$
#25
0$
1&
b100010010001000110011010001000101010101100110011101111000100010011001101010101011101111001100110111011110111011111111 %
b100010010001000110011010001000101010101100110011101111000100010011001101010101011101111001100110111011110111011111111 -
0*
#30
b10001001110110000001000011101000100001010101101011001110011010000010110100011000010000111101100011001011000100101000111111100100 1
b10001001110110000001000011101000100001010101101011001110011010000010110100011000010000111101100011001011000100101000111111100100 :
b11101101110011111100100011010 C
b11110111101111100011101100101001 J
b1010111111101011011110010010010 Q
b1011111011100100110010000010101010101111111010110111100100100101111011110111110001110110010100100011101101110011111100100011010 >
b1011111011100100110010000010101 X
b10111010 H
b11001101 O
b1001 V
b1100011 ]
b10111010 D
b11001010 E
b11010000 F
b11100111 G
b11001101 K
b1110000 L
b10110111 M
b1010001 N
b1001 R
b1100000 S
b11100001 T
b100 U
b1100011 Y
b1010011 Z
b11100000 [
b10001100 \
b10111010110010101101000011100111 B
b11001101011100001011011101010001 I
b1001011000001110000100000100 P
b1100011010100111110000010001100 W
b1100011010100111110000010001100000010010110000011100001000001001100110101110000101101110101000110111010110010101101000011100111 <
b1100011110010101011011100000100 h
b0 i
b1001010100111101000001010001 e
b1000000 f
b11001101011000001110000011100111 b
b10000000 c
b1100011110010101011011100000100000010010101001111010000010100011100110101100000111000001110011110111010011100001110000110001100 =
b10111010011100001110000110001100 _
b11000000 `
b1100010001110001011101111110110 ?
b1100010001110001011101111110110 k
b10101011 l
b10110110100100101100111100001011011001000011110110111101111100011011111010011011110001010000000001101000001100001011001111111110 0
b10110110100100101100111100001011011001000011110110111101111100011011111010011011110001010000000001101000001100001011001111111110 @
b100000010000000110000 g
b1000000010100000110000001110000 d
b10000000100100001010000010110000 a
b11000000110100001110000011110000 ^
b10101011011101101111111011010110 j
b10 A
1#
12
b100000010000000110000010000000101000001100000011100001000000010010000101000001011000011000000110100001110000011110000 "
b100000010000000110000010000000101000001100000011100001000000010010000101000001011000011000000110100001110000011110000 .
b100000010000000110000010000000101000001100000011100001000000010010000101000001011000011000000110100001110000011110000 3
b100000010000000110000010000000101000001100000011100001000000010010000101000001011000011000000110100001110000011110000 9
b11010110101010100111010011111101110100101010111101110010111110101101101010100110011110001111000111010110101010110111011011111110 6
b11010110101010100111010011111101110100101010111101110010111110101101101010100110011110001111000111010110101010110111011011111110 ;
b10 7
b10 8
1$
#35
0$
#40
b11111 H
b1110111001110101101000000001001 C
b11011000 O
b1100100010100010101000111111010 J
b10010111 V
b110001110110000110101001010001 Q
b10100111 ]
b11111111100001111001011010000100001100011101100001101010010100010110010001010001010100011111101001110111001110101101000000001001 >
b11111111100001111001011010000100 X
b11111 D
b1100001 E
b10001011 F
b1100001 G
b11011000 K
b11001001 L
b11001010 M
b1000101 N
b10010111 R
b10101101 S
b1110011 T
b10011011 U
b10100111 Y
b10111110 Z
b11010 [
b1101001 \
b11111011000011000101101100001 B
b11011000110010011100101001000101 I
b10010111101011010111001110011011 P
b10100111101111100001101001101001 W
b10100111101111100001101001101001100101111010110101110011100110111101100011001001110010100100010100011111011000011000101101100001 <
b100011011011011101101000101 ?
b100011011011011101101000101 k
b110000 l
b10100111011000011100101010011011 h
b10001001 i
b10010111101111101000101101000101 e
b10000101 f
b11011000101011010001101001100001 b
b101101 c
b10100111011000011100101010011011100101111011111010001011010001011101100010101101000110100110000100011111110010010111001101101001 =
b11111110010010111001101101001 _
b11001011 `
b10110110111111110111010001001110110100101100001011001001101111110110110001011001000011001011111100000100011010011011111101000001 0
b10110110111111110111010001001110110100101100001011001001101111110110110001011001000011001011111100000100011010011011111101000001 @
b1001001000101010101100110001111010101011110010111010111101000001101101011001010100101001111101000011111000010100110001111110111 1
b1001001000101010101100110001111010101011110010111010111101000001101101011001010100101001111101000011111000010100110001111110111 :
b110000101100111111111001101000 j
b100 A
b10001001110110000001000011101000 g
b10000101010110101100111001101000 d
b101101000110000100001111011000 a
b11001011000100101000111111100100 ^
b10110110100100101100111100001011011001000011110110111101111100011011111010011011110001010000000001101000001100001011001111111110 6
b10110110100100101100111100001011011001000011110110111101111100011011111010011011110001010000000001101000001100001011001111111110 ;
b100 7
b100 8
b10001001110110000001000011101000100001010101101011001110011010000010110100011000010000111101100011001011000100101000111111100100 "
b10001001110110000001000011101000100001010101101011001110011010000010110100011000010000111101100011001011000100101000111111100100 .
b10001001110110000001000011101000100001010101101011001110011010000010110100011000010000111101100011001011000100101000111111100100 3
b10001001110110000001000011101000100001010101101011001110011010000010110100011000010000111101100011001011000100101000111111100100 9
1$
#45
0$
#50
b11000000 H
b1010011010011011111001001010110 C
b1010111 O
b101100001111111000011010001110 J
b11111100 V
b11110111011100011111000001110110 Q
b111011 ]
b1001100100111000001111001100110111101110111000111110000011101100010110000111111100001101000111001010011010011011111001001010110 >
b1001100100111000001111001100110 X
b11000000 D
b1011001 E
b1110 F
b101101 G
b1010111 K
b1100111 L
b11001011 M
b11100000 N
b11111100 R
b1110100 S
b11111011 T
b1110011 U
b111011 Y
b11011001 Z
b100010 [
b1101000 \
b11000000010110010000111000101101 B
b1010111011001111100101111100000 I
b11111100011101001111101101110011 P
b111011110110010010001001101000 W
b111011110110010010001001101000111111000111010011111011011100110101011101100111110010111110000011000000010110010000111000101101 <
b11111001000010001000001111110010 ?
b11111001000010001000001111110010 k
b1101001 l
b111011010110011100101101110011 h
b1001001 i
b11111100110110010000111011100000 e
b1010101 f
b1010111011101000010001000101101 b
b11011010 c
b111011010110011100101101110011111111001101100100001110111000000101011101110100001000100010110111000000011001111111101101101000 =
b11000000011001111111101101101000 _
b11111 `
b1000111111101111111011110111100100101010011010100111110000000111111100101101100001100101011110011111101000001011000110111111101 0
b1000111111101111111011110111100100101010011010100111110000000111111100101101100001100101011110011111101000001011000110111111101 @
b11111010011000110110101000101000001001011011001100111001110010010100000001100110100010100011000101010111001001000100110100010111 1
b11111010011000110110101000101000001001011011001100111001110010010100000001100110100010100011000101010111001001000100110100010111 :
b1101001101111110100000100000100 j
b1000 A
b1001001000101010101100110001111 g
b1010101111001011101011110100000 d
b11011010110010101001010011111010 a
b11111000010100110001111110111 ^
b10110110111111110111010001001110110100101100001011001001101111110110110001011001000011001011111100000100011010011011111101000001 6
b10110110111111110111010001001110110100101100001011001001101111110110110001011001000011001011111100000100011010011011111101000001 ;
b1000 7
b1000 8
b1001001000101010101100110001111010101011110010111010111101000001101101011001010100101001111101000011111000010100110001111110111 "
b1001001000101010101100110001111010101011110010111010111101000001101101011001010100101001111101000011111000010100110001111110111 .
b1001001000101010101100110001111010101011110010111010111101000001101101011001010100101001111101000011111000010100110001111110111 3
b1001001000101010101100110001111010101011110010111010111101000001101101011001010100101001111101000011111000010100110001111110111 9
1$
#55
0$
#60
b1011011 H
b1110101010001111101011010010001 C
b1001 O
b10010111101111100100011110001110 J
b111111 V
b11111100010100111000110111111001 Q
b101101 ]
b1100011100001011011011110011111111111000101001110001101111110011001011110111110010001111000111001110101010001111101011010010001 >
b1100011100001011011011110011111 X
b1011011 D
b11111011 E
b10010 F
b11000111 G
b1001 K
b110110 L
b10 M
b11011101 N
b111111 R
b110011 S
b11100011 T
b110100 U
b101101 Y
b1101101 Z
b1111110 [
b11110000 \
b1011011111110110001001011000111 B
b1001001101100000001011011101 I
b111111001100111110001100110100 P
b101101011011010111111011110000 W
b101101011011010111111011110000001111110011001111100011001101000000100100110110000000101101110101011011111110110001001011000111 <
b1101011010111010101010001010100 ?
b1101011010111010101010001010100 k
b101 l
b101101111110110000001000110100 h
b11111010 i
b111111011011010001001011011101 e
b100101 f
b1001001100110111111011000111 b
b1000000 c
b101101111110110000001000110100001111110110110100010010110111010000100100110011011111101100011101011011001101101110001111110000 =
b1011011001101101110001111110000 _
b1010111 `
b111100101010101010001111101000101010011001111110011101111010110101000011110011101011110101011110101101111101100010001010101010 0
b111100101010101010001111101000101010011001111110011101111010110101000011110011101011110101011110101101111101100010001010101010 @
b100100011100100100000000100011011010010110011010110011111110100110111011010010011101010011001010001000010000100101101101101100 1
b100100011100100100000000100011011010010110011010110011111110100110111011010010011101010011001010001000010000100101101101101100 :
b101100011011111110111111101 j
b10000 A
b11111010011000110110101000101000 g
b100101101100110011100111001001 d
b1000000011001101000101000110001 a
b1010111001001000100110100010111 ^
b1000111111101111111011110111100100101010011010100111110000000111111100101101100001100101011110011111101000001011000110111111101 6
b1000111111101111111011110111100100101010011010100111110000000111111100101101100001100101011110011111101000001011000110111111101 ;
b10000 7
b10000 8
b11111010011000110110101000101000001001011011001100111001110010010100000001100110100010100011000101010111001001000100110100010111 "
b11111010011000110110101000101000001001011011001100111001110010010100000001100110100010100011000101010111001001000100110100010111 .
b11111010011000110110101000101000001001011011001100111001110010010100000001100110100010100011000101010111001001000100110100010111 3
b11111010011000110110101000101000001001011011001100111001110010010100000001100110100010100011000101010111001001000100110100010111 9
1$
#65
0$
#70
b11000100 H
b11101110100000011101100111100 C
b10011111 O
b1110101111100011101011011000101 J
b11111001 V
b110010111001010101010011010000 Q
b110110 ]
b11110100101111001101010001010100001100101110010101010100110100000111010111110001110101101100010100011101110100000011101100111100 >
b11110100101111001101010001010100 X
b11000100 D
b1000000 E
b1101101 F
b100011 G
b10011111 K
b101100 L
b1001 M
b101101 N
b11111001 R
b10110101 S
b111001 T
b100110 U
b110110 Y
b110011 Z
b10011101 [
b1010000 \
b11000100010000000110110100100011 B
b10011111001011000000100100101101 I
b11111001101101010011100100100110 P
b110110001100111001110101010000 W
b110110001100111001110101010000111110011011010100111001001001101001111100101100000010010010110111000100010000000110110100100011 <
b1000010100100111010110010010101 ?
b1000010100100111010110010010101 k
b11110110 l
b110110010000000000100100100110 h
b100100 i
b11111001001100110110110100101101 e
b1101001 f
b10011111101101011001110100100011 b
b1101110 c
b110110010000000000100100100110111110010011001101101101001011011001111110110101100111010010001111000100001011000011100101010000 =
b11000100001011000011100101010000 _
b10001000 `
b1011110001110010000111101111101111101111010011010010010100101101010011101010101001111011100000100001010101000110001111101101011 0
b1011110001110010000111101111101111101111010011010010010100101101010011101010101001111011100000100001010101000110001111101101011 @
b11001000000101100111011110111100100110110111101011001001001110110010010100000010011110011001001010110000001001100001100110010110 1
b11001000000101100111011110111100100110110111101011001001001110110010010100000010011110011001001010110000001001100001100110010110 :
b11110110001000101010101010101101 j
b100000 A
b100100011100100100000000100011 g
b1101001011001101011001111111010 d
b1101110110100100111010100110010 a
b10001000010000100101101101101100 ^
b111100101010101010001111101000101010011001111110011101111010110101000011110011101011110101011110101101111101100010001010101010 6
b111100101010101010001111101000101010011001111110011101111010110101000011110011101011110101011110101101111101100010001010101010 ;
b100000 7
b100000 8
b100100011100100100000000100011011010010110011010110011111110100110111011010010011101010011001010001000010000100101101101101100 "
b100100011100100100000000100011011010010110011010110011111110100110111011010010011101010011001010001000010000100101101101101100 .
b100100011100100100000000100011011010010110011010110011111110100110111011010010011101010011001010001000010000100101101101101100 3
b100100011100100100000000100011011010010110011010110011111110100110111011010010011101010011001010001000010000100101101101101100 9
1$
#75
0$
#80
b11100111 H
b10001110010110101101000000110110 C
b111111 O
b1101011001011000000010010011100 J
b10100 V
b111110000111111101010101 Q
b11101000 ]
b10011000000101101110111001110100000000001111100001111111010101010110101100101100000001001001110010001110010110101101000000110110 >
b10011000000101101110111001110100 X
b11100111 D
b1000111 E
b11011101 F
b1001111 G
b111111 K
b11110111 L
b11110101 M
b11100010 N
b10100 R
b1110111 S
b11010100 T
b1100101 U
b11101000 Y
b11011010 Z
b10110110 [
b10010000 \
b11100111010001111101110101001111 B
b111111111101111111010111100010 I
b10100011101111101010001100101 P
b11101000110110101011011010010000 W
b11101000110110101011011010010000000101000111011111010100011001010011111111110111111101011110001011100111010001111101110101001111 <
b1010110000000111111101100111 ?
b1010110000000111111101100111 k
b10100011 l
b11101000010001111111010101100101 h
b11001000 i
b10100110110101101110111100010 e
b10011011 f
b111111011101111011011001001111 b
b100101 c
b11101000010001111111010101100101000101001101101011011101111000100011111101110111101101100100111111100111111101111101010010010000 =
b11100111111101111101010010010000 _
b10110000 `
b10100111110010111000000011010111000110101111111100010100011000100010000001010110111110100110101001110101010011100000000100110 0
b10100111110010111000000011010111000110101111111100010100011000100010000001010110111110100110101001110101010011100000000100110 @
b11000110001011111110000100001001111101110101111011101101110000111100110001111001001110010101110110000100111110011100111101011101 1
b11000110001011111110000100001001111101110101111011101101110000111100110001111001001110010101110110000100111110011100111101011101 :
b10100011000111110110101100001010 j
b1000000 A
b11001000000101100111011110111100 g
b10011011011110101100100100111011 d
b100101000000100111100110010010 a
b10110000001001100001100110010110 ^
b1011110001110010000111101111101111101111010011010010010100101101010011101010101001111011100000100001010101000110001111101101011 6
b1011110001110010000111101111101111101111010011010010010100101101010011101010101001111011100000100001010101000110001111101101011 ;
b1000000 7
b1000000 8
b11001000000101100111011110111100100110110111101011001001001110110010010100000010011110011001001010110000001001100001100110010110 "
b11001000000101100111011110111100100110110111101011001001001110110010010100000010011110011001001010110000001001100001100110010110 .
b11001000000101100111011110111100100110110111101011001001001110110010010100000010011110011001001010110000001001100001100110010110 3
b11001000000101100111011110111100100110110111101011001001001110110010010100000010011110011001001010110000001001100001100110010110 9
1$
#85
0$
