verilog-stream/verilog-stream-cipher/stream_cipher.v

module A5(
    input wire rest,
    input wire clk,  //时钟信号
    input wire [63:0] Key,  //初始化密钥
    output  wire code
);



reg[18:0] A;
reg[21:0] B;
reg[22:0] C;
reg X;
reg Y;
reg Z;
reg  re;
reg condition1;
reg condition2;
reg condition3;
reg feedback1,feedback2,feedback3;


always @(posedge clk or rest ) begin
    if(rest)
    begin
    A = Key[18:0];
    B = Key[40:19];
    C = Key[63:41];
    end
    //initialize the key
    X = A[8];
    Y = B[10];
    Z = C[10];
    //generate round key
    re = A[18]^B[21]^C[22];
    //feedback condition judgement
    //use clocking bit 
    condition1 = ((~X)&(~Y))|(X&Z)|(Y&(~Z));
    condition2 = ((~Y)&(~Z))|((~X)&Y)|(X&Y);
    condition3 = ((~Y)&(~Z))|(X&Z)|(Y&(~X));
    if(condition1 == 1'b1)
    begin
        feedback1 = A[18]^A[17]^A[16]^A[13];
        A = {A[17:0],feedback1};
    end
    if(condition2 == 1'b1)
    begin
        feedback2 = B[21]^B[20];
        B = {B[20:0],feedback2};
    end
    if(condition3 == 1'b1)
    begin
        feedback3 = C[21]^C[20]^C[22]^C[7];
        C = {C[21:0],feedback3};
    end
    
end
    assign code = re;

endmodule

verilog-stream/verilog-stream-cipher/textbench.v
`timescale 1ns/1ps
`include "stream_cipher.v"


module text();
    reg  clk;
    reg rest;
    wire  dataout;
    reg [63:0] Key;

    //clock generating
    real CYCLE_200MHZ =5;
    always begin
        clk = 0;#(CYCLE_200MHZ/2);
        clk = 1;#(CYCLE_200MHZ/2);
    end

    initial begin
        Key = 64'h3170604015ABCDEF;
        //initialize the key and h express the hex .
        rest = 1;
        #100 //after 100ns end the reset process.
        rest = 0;
    end
    

    A5 A5text(
        .rest      (rest),
        .clk       (clk),
        .Key    (Key),
        .code     (dataout)

    );

    initial begin
        forever begin
            #100
            if($time >= 1000) $finish;
        end
    end

    initial begin
        $dumpfile("wave.vcd");
        //check the wave of the module.
        $dumpvars;
    end



endmodule

verilog-stream/verilog-stream-cipher/wave.vcd
$date
	Mon Oct 24 21:42:58 2022
$end
$version
	Icarus Verilog
$end
$timescale
	1ps
$end
$scope module text $end
$var wire 1 ! dataout $end
$var reg 64 " Key [63:0] $end
$var reg 1 # clk $end
$var reg 1 $ rest $end
$var real 1 % CYCLE_200MHZ $end
$scope module A5text $end
$var wire 64 & Key [63:0] $end
$var wire 1 # clk $end
$var wire 1 ! code $end
$var wire 1 $ rest $end
$var reg 19 ' A [18:0] $end
$var reg 22 ( B [21:0] $end
$var reg 23 ) C [22:0] $end
$var reg 1 * X $end
$var reg 1 + Y $end
$var reg 1 , Z $end
$var reg 1 - condition1 $end
$var reg 1 . condition2 $end
$var reg 1 / condition3 $end
$var reg 1 0 feedback1 $end
$var reg 1 1 feedback2 $end
$var reg 1 2 feedback3 $end
$var reg 1 3 re $end
$upscope $end
$upscope $end
$enddefinitions $end
#0
$dumpvars
03
12
01
x0
1/
1.
0-
0,
0+
1*
b1100010111000001100001 )
b100000000010101101010 (
b111100110111101111 '
b11000101110000011000000100000000010101101010111100110111101111 &
r5 %
1$
0#
b11000101110000011000000100000000010101101010111100110111101111 "
0!
$end
#2500
b1100010111000001100001 )
b100000000010101101010 (
1#
#5000
0#
#7500
b1100010111000001100001 )
b100000000010101101010 (
1#
#10000
0#
#12500
b1100010111000001100001 )
b100000000010101101010 (
1#
#15000
0#
#17500
b1100010111000001100001 )
b100000000010101101010 (
1#
#20000
0#
#22500
b1100010111000001100001 )
b100000000010101101010 (
1#
#25000
0#
#27500
b1100010111000001100001 )
b100000000010101101010 (
1#
#30000
0#
#32500
b1100010111000001100001 )
b100000000010101101010 (
1#
#35000
0#
#37500
b1100010111000001100001 )
b100000000010101101010 (
1#
#40000
0#
#42500
b1100010111000001100001 )
b100000000010101101010 (
1#
#45000
0#
#47500
b1100010111000001100001 )
b100000000010101101010 (
1#
#50000
0#
#52500
b1100010111000001100001 )
b100000000010101101010 (
1#
#55000
0#
#57500
b1100010111000001100001 )
b100000000010101101010 (
1#
#60000
0#
#62500
b1100010111000001100001 )
b100000000010101101010 (
1#
#65000
0#
#67500
b1100010111000001100001 )
b100000000010101101010 (
1#
#70000
0#
#72500
b1100010111000001100001 )
b100000000010101101010 (
1#
#75000
0#
#77500
b1100010111000001100001 )
b100000000010101101010 (
1#
#80000
0#
#82500
b1100010111000001100001 )
b100000000010101101010 (
1#
#85000
0#
#87500
b1100010111000001100001 )
b100000000010101101010 (
1#
#90000
0#
#92500
b1100010111000001100001 )
b100000000010101101010 (
1#
#95000
0#
#97500
b1100010111000001100001 )
b100000000010101101010 (
1#
#100000
b1000000000101011010101 (
11
b1111001101111011110 '
00
0/
1-
1+
0#
0$
#102500
b11000101110000011000010 )
02
b1010110101011 (
1/
0-
0+
1#
#105000
0#
#107500
b10101101010110 (
01
b1110011011110111101 '
10
0/
1-
1+
1#
#110000
0#
#112500
b10001011100000110000101 )
12
b101011010101100 (
1/
0-
0+
1#
#115000
0#
#117500
b1010110101011000 (
b1100110111101111010 '
00
0/
1-
1+
1#
#120000
0#
#122500
b10101101010110000 (
b1001101111011110101 '
10
1#
#125000
0#
#127500
b10111000001100001010 )
02
b101011010101100000 (
b11011110111101011 '
1/
0+
0*
1#
#130000
0#
#132500
b1010110101011000000 (
b110111101111010110 '
00
0/
1+
1*
1#
#135000
0#
#137500
b101110000011000010100 )
b10101101010110000000 (
1/
0-
0+
1#
#140000
0#
#142500
b1011100000110000101001 )
12
b101011010101100000000 (
b1101111011110101101 '
10
1-
1,
1+
1#
#145000
0#
#147500
b10111000001100001010011 )
b1011110111101011011 '
0.
1!
13
0+
1#
#150000
0#
#152500
b1110000011000010100110 )
02
b1010110101011000000001 (
11
1.
0-
0!
03
0,
1#
#155000
0#
#157500
b101101010110000000011 (
b111101111010110111 '
0/
1-
1+
1#
#160000
0#
#162500
b11100000110000101001101 )
12
b1011010101100000000111 (
b1111011110101101110 '
00
1/
0*
1#
#165000
0#
#167500
b11000001100001010011011 )
b110101011000000001111 (
0-
1!
13
0+
1*
1#
#170000
0#
#172500
b10000011000010100110111 )
b1101010110000000011111 (
0!
03
1#
#175000
0#
#177500
b110000101001101111 )
b1110111101011011100 '
0.
1-
1!
13
1,
1#
#180000
0#
#182500
b1100001010011011110 )
02
b1010101100000000111110 (
01
b1101111010110111000 '
1.
0!
03
0,
0*
1#
#185000
0#
#187500
b11000010100110111101 )
12
b1011110101101110001 '
10
0.
1,
1*
1#
#190000
0#
#192500
b110000101001101111011 )
b101011000000001111101 (
11
1.
0-
0,
1#
#195000
0#
#197500
b1100001010011011110111 )
b1010110000000011111011 (
1!
13
1#
#200000
0#
#202500
b11000010100110111101111 )
b111101011011100011 '
0.
1-
0!
03
1,
1#
#205000
0#
#207500
b1111010110111000110 '
00
0/
0*
1#
#210000
0#
#212500
b10000101001101111011111 )
b1110101101110001100 '
1/
1!
13
1*
1#
#215000
0#
#217500
b1010011011110111110 )
02
b101100000000111110111 (
1.
0-
0,
1#
#220000
0#
#222500
b10100110111101111101 )
12
b1101011011100011001 '
10
0.
1-
1,
1#
#225000
0#
#227500
b101001101111011111010 )
02
b1010110111000110011 '
1#
#230000
0#
#232500
b101101110001100111 '
0/
0*
1#
#235000
0#
#237500
b1011011100011001111 '
0!
03
1#
#240000
0#
#242500
b110111000110011111 '
1!
13
1#
#245000
0#
#247500
b1010011011110111110100 )
b1101110001100111111 '
1/
0!
03
1*
1#
#250000
0#
#252500
b10100110111101111101000 )
b1011100011001111111 '
1!
13
1#
#255000
0#
#257500
b1001101111011111010001 )
12
b1011000000001111101111 (
b111000110011111110 '
00
1.
0!
03
0,
0*
1#
#260000
0#
#262500
b1110001100111111100 '
0/
0.
1!
13
1,
1#
#265000
0#
#267500
b10011011110111110100010 )
02
b1100011001111111001 '
10
1/
0!
03
1*
1#
#270000
0#
#272500
b110111101111101000100 )
b1000110011111110011 '
1!
13
1#
#275000
0#
#277500
b1101111011111010001001 )
12
b1100111111100110 '
00
0!
03
1#
#280000
0#
#282500
b11011110111110100010011 )
b11001111111001100 '
1!
13
1#
#285000
0#
#287500
b10111101111101000100110 )
02
b110011111110011001 '
10
0!
03
1#
#290000
0#
#292500
b1111011111010001001100 )
b110000000011111011111 (
1.
0-
0,
1#
#295000
0#
#297500
b11110111110100010011000 )
b1100000000111110111111 (
b1100111111100110011 '
1-
1,
1+
1#
#300000
0#
#302500
b1000000001111101111110 (
01
b1001111111001100111 '
0/
1!
13
0,
1#
#305000
0#
#307500
b11101111101000100110000 )
b11111011111101 (
11
b11111110011001110 '
00
1/
0*
1#
#310000
0#
#312500
b11011111010001001100001 )
12
b111110111111010 (
01
b111111100110011100 '
1#
#315000
0#
#317500
b1111101111110100 (
b1111111001100111001 '
10
0/
1*
1#
#320000
0#
#322500
b10111110100010011000010 )
02
b11111011111101000 (
1/
0-
0!
03
0+
1#
#325000
0#
#327500
b1111101000100110000101 )
12
b111110111111010000 (
b1111110011001110010 '
00
1-
1,
1+
1#
#330000
0#
#332500
b11111010001001100001011 )
b1111101111110100000 (
b1111100110011100100 '
1!
13
0,
0*
1#
#335000
0#
#337500
b11110100010011000010111 )
b11111011111101000000 (
b1111001100111001001 '
10
0!
03
1#
#340000
0#
#342500
b11101000100110000101111 )
b111110111111010000000 (
b1110011001110010011 '
1,
1*
1#
#345000
0#
#347500
b11010001001100001011111 )
b1111101111110100000001 (
11
b1100110011100100110 '
00
1#
#350000
0#
#352500
b1111011111101000000010 (
01
b1001100111001001101 '
10
0/
1!
13
0,
1#
#355000
0#
#357500
b10100010011000010111110 )
02
b1110111111010000000100 (
b11001110010011011 '
1/
0+
0*
1#
#360000
0#
#362500
b1000100110000101111101 )
12
b1101111110100000001000 (
b110011100100110111 '
0!
03
1+
1#
#365000
0#
#367500
b10001001100001011111011 )
b1011111101000000010000 (
0-
1!
13
0+
1*
1#
#370000
0#
#372500
b10011000010111110110 )
02
b111111010000000100001 (
11
0!
03
1#
#375000
0#
#377500
b100110000101111101101 )
12
b1100111001001101111 '
0.
1-
1,
1#
#380000
0#
#382500
b1001100001011111011010 )
02
b1111110100000001000011 (
b1001110010011011111 '
1.
1!
13
0,
0*
1#
#385000
0#
#387500
b11100100110111110 '
00
0/
0.
0!
03
1,
1#
#390000
0#
#392500
b10011000010111110110100 )
b111001001101111101 '
10
1/
1!
13
1*
1#
#395000
0#
#397500
b110000101111101101000 )
b1110010011011111010 '
00
0!
03
1#
#400000
0#
#402500
b1100100110111110100 '
0/
0*
1#
#405000
0#
#407500
b1100001011111011010001 )
12
b1001001101111101000 '
1/
1*
1#
#410000
0#
#412500
b11000010111110110100011 )
b10011011111010001 '
10
1#
#415000
0#
#417500
b10000101111101101000111 )
b100110111110100010 '
00
1#
#420000
0#
#422500
b1011111011010001111 )
b1111101000000010000110 (
01
1.
0-
0,
1#
#425000
0#
#427500
b10111110110100011111 )
b1001101111101000100 '
0.
1-
1!
13
1,
1#
#430000
0#
#432500
b101111101101000111110 )
02
b11011111010001001 '
10
0!
03
1#
#435000
0#
#437500
b1011111011010001111101 )
12
b1111010000000100001100 (
b110111110100010010 '
00
1.
1!
13
0,
0*
1#
#440000
0#
#442500
b10111110110100011111011 )
b1101111101000100101 '
10
0.
1,
1*
1#
#445000
0#
#447500
b1111101101000111110111 )
b1110100000001000011000 (
b1011111010001001011 '
1.
0,
0*
1#
#450000
0#
#452500
b11111011010001111101111 )
b1101000000010000110000 (
b111110100010010111 '
0!
03
1#
#455000
0#
#457500
b11110110100011111011110 )
02
b1010000000100001100000 (
b1111101000100101111 '
1+
1#
#460000
0#
#462500
b11101101000111110111100 )
b1111010001001011111 '
0.
1!
13
1,
0+
1*
1#
#465000
0#
#467500
b1110100010010111110 '
00
0/
0*
1#
#470000
0#
#472500
b1101000100101111101 '
10
1#
#475000
0#
#477500
b11011010001111101111000 )
b1010001001011111010 '
00
1/
1*
1#
#480000
0#
#482500
b100010010111110100 '
0/
0*
1#
#485000
0#
#487500
b10110100011111011110000 )
b1000100101111101000 '
1/
0!
03
1*
1#
#490000
0#
#492500
b1101000111110111100001 )
12
b1001011111010001 '
10
1!
13
1#
#495000
0#
#497500
b11010001111101111000011 )
b10010111110100010 '
00
1#
#500000
0#
#502500
b10100011111011110000111 )
b100000001000011000001 (
11
1.
0-
0!
03
0,
1#
#505000
0#
#507500
b1000111110111100001111 )
b100101111101000100 '
0.
1-
1!
13
1,
1#
#510000
0#
#512500
b10001111101111000011111 )
b1001011111010001001 '
10
0!
03
1#
#515000
0#
#517500
b10111110100010010 '
00
0/
0*
1#
#520000
0#
#522500
b11111011110000111111 )
b101111101000100100 '
1/
1!
13
1*
1#
#525000
0#
#527500
b1011111010001001000 '
0/
0!
03
0*
1#
#530000
0#
#532500
b111110100010010001 '
10
1!
13
1#
#535000
0#
#537500
b1111101000100100011 '
0!
03
1#
#540000
0#
#542500
b111110111100001111110 )
02
b1111010001001000111 '
1/
1!
13
1*
1#
#545000
0#
#547500
b1111101111000011111101 )
12
b1000000010000110000011 (
b1110100010010001110 '
00
1.
0,
0*
1#
#550000
0#
#552500
b11111011110000111111011 )
b100001100000111 (
b1101000100100011101 '
10
0!
03
1#
#555000
0#
#557500
b11110111100001111110110 )
02
b1000011000001110 (
01
0-
1*
1#
#560000
0#
#562500
b10000110000011100 (
b1010001001000111010 '
00
0/
1-
1+
1#
#565000
0#
#567500
b11101111000011111101100 )
b100001100000111000 (
b100010010001110100 '
1/
0*
1#
#570000
0#
#572500
b1000100100011101000 '
0/
0.
1!
13
1,
0+
1#
#575000
0#
#577500
b1001000111010001 '
10
0!
03
1#
#580000
0#
#582500
b11011110000111111011000 )
b10010001110100010 '
00
1/
1!
13
1*
1#
#585000
0#
#587500
b10111100001111110110001 )
12
b100100011101000100 '
1#
#590000
0#
#592500
b1111000011111101100011 )
b1001000111010001001 '
10
1#
#595000
0#
#597500
b10001110100010011 '
0/
0*
1#
#600000
0#
#602500
b11110000111111011000110 )
02
b100011101000100111 '
1/
0!
03
1*
1#
#605000
0#
#607500
b1000111010001001110 '
00
0/
1!
13
0*
1#
#610000
0#
#612500
b1110100010011100 '
0!
03
1#
#615000
0#
#617500
b11101000100111001 '
10
1!
13
1#
#620000
0#
#622500
b11100001111110110001100 )
b111010001001110011 '
1/
1*
1#
#625000
0#
#627500
b1110100010011100111 '
0/
0*
1#
#630000
0#
#632500
b1101000100111001111 '
0!
03
1#
#635000
0#
#637500
b11000011111101100011000 )
b1010001001110011110 '
00
1/
1*
1#
#640000
0#
#642500
b10000111111011000110000 )
b1000011000001110000 (
1.
0-
0,
1#
#645000
0#
#647500
b1111110110001100001 )
12
b100010011100111100 '
0.
1-
1,
1#
#650000
0#
#652500
b11111101100011000010 )
02
b1000100111001111000 '
1#
#655000
0#
#657500
b111111011000110000101 )
12
b10000110000011100000 (
b1001110011110001 '
10
1.
1!
13
0,
0*
1#
#660000
0#
#662500
b1111110110001100001010 )
02
b100001100000111000000 (
b10011100111100010 '
00
0!
03
1#
#665000
0#
#667500
b11111101100011000010100 )
b1000011000001110000001 (
11
0-
1*
1#
#670000
0#
#672500
b11111011000110000101001 )
12
b100111001111000100 '
0.
1-
1,
1#
#675000
0#
#677500
b11110110001100001010011 )
b1001110011110001000 '
1#
#680000
0#
#682500
b11101100011000010100111 )
b110000011100000011 (
1.
0-
1!
13
0,
1#
#685000
0#
#687500
b1100000111000000110 (
01
b11100111100010000 '
0/
1-
0!
03
1+
1#
#690000
0#
#692500
b11000001110000001100 (
b111001111000100001 '
10
1!
13
1#
#695000
0#
#697500
b11011000110000101001110 )
02
b110000011100000011000 (
b1110011110001000010 '
00
1/
0*
1#
#700000
0#
#702500
b10110001100001010011100 )
b1100000111000000110001 (
11
b1100111100010000100 '
0!
03
0+
1#
#705000
0#
#707500
b1100011000010100111001 )
12
b1000001110000001100010 (
01
b1001111000100001001 '
10
1!
13
1#
#710000
0#
#712500
b11000110000101001110010 )
02
b11110001000010010 '
00
0.
0!
03
1,
1*
1#
#715000
0#
#717500
b10001100001010011100100 )
b11100000011000101 (
11
b111100010000100100 '
1.
0,
0*
1#
#720000
0#
#722500
b1111000100001001000 '
0/
0.
1!
13
1,
1#
#725000
0#
#727500
b1110001000010010001 '
10
0!
03
1#
#730000
0#
#732500
b1100010000100100011 '
1#
#735000
0#
#737500
b11000010100111001000 )
b1000100001001000111 '
1/
1*
1#
#740000
0#
#742500
b110000101001110010001 )
12
b111000000110001010 (
01
b1000010010001111 '
1.
1!
13
0,
0*
1#
#745000
0#
#747500
b1100001010011100100010 )
02
b1110000001100010100 (
b10000100100011110 '
00
0!
03
1#
#750000
0#
#752500
b11000010100111001000100 )
b100001001000111101 '
10
0.
1,
1*
1#
#755000
0#
#757500
b1000010010001111011 '
0/
1!
13
0*
1#
#760000
0#
#762500
b100100011110110 '
00
0!
03
1#
#765000
0#
#767500
b1001000111101100 '
1!
13
1#
#770000
0#
#772500
b10000101001110010001000 )
b10010001111011000 '
1/
1*
1#
#775000
0#
#777500
b1010011100100010000 )
b100100011110110000 '
1#
#780000
0#
#782500
b10100111001000100000 )
b11100000011000101000 (
1.
0-
0!
03
0,
1#
#785000
0#
#787500
b111000000110001010000 (
b1001000111101100001 '
10
0/
1-
1+
1#
#790000
0#
#792500
b1110000001100010100001 (
11
b10001111011000011 '
1!
13
1#
#795000
0#
#797500
b101001110010001000000 )
b1100000011000101000010 (
01
b100011110110000111 '
1/
0+
0*
1#
#800000
0#
#802500
b1010011100100010000001 )
12
b1000111101100001110 '
00
0.
1,
1*
1#
#805000
0#
#807500
b10100111001000100000010 )
02
b1000000110001010000100 (
1.
0-
0!
03
0,
1#
#810000
0#
#812500
b1001110010001000000100 )
b1100010100001001 (
11
1!
13
1#
#815000
0#
#817500
b11000101000010010 (
01
b1111011000011100 '
0/
1-
1+
1#
#820000
0#
#822500
b10011100100010000001001 )
12
b110001010000100100 (
b11110110000111001 '
10
1/
0!
03
0+
0*
1#
#825000
0#
#827500
b111001000100000010011 )
b1100010100001001000 (
0-
1!
13
1,
1+
1#
#830000
0#
#832500
b1110010001000000100111 )
b11000101000010010000 (
b111101100001110010 '
00
1-
0!
03
0,
0+
1#
#835000
0#
#837500
b11100100010000001001110 )
02
b110001010000100100000 (
b1111011000011100100 '
1#
#840000
0#
#842500
b11001000100000010011101 )
12
b1100010100001001000001 (
11
b1110110000111001000 '
1#
#845000
0#
#847500
b10010001000000100111011 )
b1000101000010010000010 (
01
0-
1!
13
1*
1#
#850000
0#
#852500
b1010000100100000101 (
11
b1101100001110010000 '
0/
1-
1+
1#
#855000
0#
#857500
b100010000001001110111 )
b10100001001000001010 (
01
1/
0-
0!
03
0+
1#
#860000
0#
#862500
b1000100000010011101111 )
b101000010010000010100 (
1!
13
1#
#865000
0#
#867500
b10001000000100111011110 )
02
b1010000100100000101001 (
11
b1011000011100100000 '
1-
1,
1+
1#
#870000
0#
#872500
b10000001001110111100 )
b100001001000001010011 (
0-
0,
0+
1#
#875000
0#
#877500
b100000010011101111001 )
12
b1000010010000010100111 (
1#
#880000
0#
#882500
b1000000100111011110011 )
b110000111001000000 '
0.
1-
0!
03
1,
1#
#885000
0#
#887500
b1100001110010000000 '
0/
1!
13
0*
1#
#890000
0#
#892500
b1000011100100000000 '
0!
03
1#
#895000
0#
#897500
b10000001001110111100110 )
02
b111001000000000 '
1/
1*
1#
#900000
0#
#902500
b1110010000000001 '
10
0/
0*
1#
#905000
0#
#907500
b11100100000000011 '
1#
#910000
0#
#912500
b111001000000000111 '
1#
#915000
0#
#917500
b1110010000000001110 '
00
1#
#920000
0#
#922500
b1100100000000011100 '
1!
13
1#
#925000
0#
#927500
b1001000000000111000 '
1#
#930000
0#
#932500
b10000000001110001 '
10
1#
#935000
0#
#937500
b100000000011100011 '
0!
03
1#
#940000
0#
#942500
b1000000000111000111 '
1#
#945000
0#
#947500
b10011101111001100 )
b1110001111 '
1/
1!
13
1*
1#
#950000
0#
#952500
b100111011110011001 )
12
b100100000101001111 (
1.
0-
0,
1#
#955000
0#
#957500
b1001110111100110011 )
b11100011110 '
00
0.
1-
0!
03
1,
1#
#960000
0#
#962500
b10011101111001100110 )
02
b111000111100 '
1#
#965000
0#
#967500
b1110001111000 '
0/
0*
1#
#970000
0#
#972500
b11100011110000 '
1#
#975000
0#
#977500
b111000111100001 '
10
1#
#980000
0#
#982500
b100111011110011001100 )
b1110001111000011 '
1/
1*
1#
#985000
0#
#987500
b1001110111100110011000 )
b11100011110000111 '
1#
#990000
0#
#992500
b10011101111001100110000 )
b1001000001010011110 (
01
1.
0-
0,
1#
#995000
0#
#997500
b111011110011001100001 )
12
b10010000010100111100 (
1!
13
1#
